{
    "4091c1a21900bd2c7d3f4e343acddda1": {
        "label": "No. 1 | Marco Cheng",
        "rank": "1",
        "score": "4,700",
        "username": "Marco Cheng"
    },
    "1247b1b5b9cd95e98d7ff7438207406f": {
        "label": "No. 2 | mr. Arman (\u68a6\u60f3)",
        "rank": "2",
        "score": "4,195",
        "username": "mr. Arman (\u68a6\u60f3)"
    },
    "2561d6c634fa6c4eb794454446029d95": {
        "label": "No. 3 | StoatScript",
        "rank": "3",
        "score": "3,935",
        "username": "StoatScript"
    },
    "bf62d15a67b58334f4927c43de7b2b43": {
        "label": "No. 4 | Niels van Galen Last",
        "rank": "4",
        "score": "3,440",
        "username": "Niels van Galen Last"
    },
    "b2a65fe50f4b769aef446ccf196c1aa9": {
        "label": "No. 5 | Lado Turmanidze (Stochastic Batman)",
        "rank": "5",
        "score": "3,350",
        "username": "Lado Turmanidze (Stochastic Batman)"
    },
    "7d9e00eae4cfbb44fb4c2c4a5a0e0e92": {
        "label": "No. 6 | ZhangJY",
        "rank": "6",
        "score": "3,350",
        "username": "ZhangJY"
    },
    "0eeb1bc570f4ebaca4c3c1d5794e9de9": {
        "label": "No. 7 | Patteera Triamamornwooth",
        "rank": "7",
        "score": "3,280",
        "username": "Patteera Triamamornwooth"
    },
    "1d225304451b31b86e367c51836e4753": {
        "label": "No. 8 | Lea Wron",
        "rank": "8",
        "score": "3,205",
        "username": "Lea Wron"
    },
    "1ee22a1a5d5b97a70b6cd528ac988570": {
        "label": "No. 9 | Siva Morgan",
        "rank": "9",
        "score": "3,020",
        "username": "Siva Morgan"
    },
    "37acd4a1f0f2ca6d878510840927ce2c": {
        "label": "No. 10 | N R",
        "rank": "10",
        "score": "3,005",
        "username": "N R"
    },
    "cff9f40845e3ff805b72d0503a206acc": {
        "label": "No. 11 | DhanushKumar .R",
        "rank": "11",
        "score": "2,990",
        "username": "DhanushKumar .R"
    },
    "704d3a24b0de71e291b1dbf2a02f2c79": {
        "label": "No. 12 | 1nkik H",
        "rank": "12",
        "score": "2,970",
        "username": "1nkik H"
    },
    "8a245f5d70036cdf1a252baf4ed2a78d": {
        "label": "No. 13 | Mahdi Farmahini Farahani",
        "rank": "13",
        "score": "2,940",
        "username": "Mahdi Farmahini Farahani"
    },
    "b8ae93affd3e88323d92b845bf69de74": {
        "label": "No. 14 | hiddenneuron",
        "rank": "14",
        "score": "2,905",
        "username": "hiddenneuron"
    },
    "c1e342b828691a76b98ed4120ad9319d": {
        "label": "No. 15 | Kuat Kurpenov",
        "rank": "15",
        "score": "2,845",
        "username": "Kuat Kurpenov"
    },
    "13295956e24479d8759ef0f127c01818": {
        "label": "No. 16 | SantaClaus",
        "rank": "16",
        "score": "2,825",
        "username": "SantaClaus"
    },
    "45f9607a6e1850d180a9c15bb6bbf5b0": {
        "label": "No. 17 | antonoof",
        "rank": "17",
        "score": "2,780",
        "username": "antonoof"
    },
    "925ab312a51a924ab68d9812baa788ff": {
        "label": "No. 18 | BY",
        "rank": "18",
        "score": "2,695",
        "username": "BY"
    },
    "7386d8d63248e711e654b3bfec33dd39": {
        "label": "No. 19 | Salim Beyden",
        "rank": "19",
        "score": "2,658.5",
        "username": "Salim Beyden"
    },
    "19bd568027a2ada74dbe041a914dc04a": {
        "label": "No. 20 | trangstalbergle",
        "rank": "20",
        "score": "2,601",
        "username": "trangstalbergle"
    },
    "16ecc996ab86da4479db325f7f17f754": {
        "label": "No. 21 | Anirudh Senani",
        "rank": "21",
        "score": "2,570",
        "username": "Anirudh Senani"
    },
    "157181ffcabbeae54bb036e489bc2b77": {
        "label": "No. 22 | PAT",
        "rank": "22",
        "score": "2,535",
        "username": "PAT"
    },
    "b0622edd2fcc61212c82fb68a60b8cf8": {
        "label": "No. 23 | jwu456789",
        "rank": "23",
        "score": "2,520",
        "username": "jwu456789"
    },
    "4ccccac4eb579273525d6e22d4d24adb": {
        "label": "No. 24 | Haolun Zhang",
        "rank": "24",
        "score": "2,510",
        "username": "Haolun Zhang"
    },
    "185b5d0948a42bd94b203fee0c45f4c0": {
        "label": "No. 25 | Maksym Koval",
        "rank": "25",
        "score": "2,510",
        "username": "Maksym Koval"
    },
    "8fd8dcf2a00e8f91fe5b2c6bb1c0aa8e": {
        "label": "No. 26 | Alexander Krylov",
        "rank": "26",
        "score": "2,505",
        "username": "Alexander Krylov"
    },
    "cce76d51f99ea50b5f1db2584fb530fe": {
        "label": "No. 27 | Loading\u2026 \u2588\u2588\u2588\u2588\u2588\u2588\u2588\u2588\u2588\u2588\u2588\u2588\u2588\u2588] 99%",
        "rank": "27",
        "score": "2,490",
        "username": "Loading\u2026 \u2588\u2588\u2588\u2588\u2588\u2588\u2588\u2588\u2588\u2588\u2588\u2588\u2588\u2588] 99%"
    },
    "dfafdfd3b0d614c7d07de6d336c5a230": {
        "label": "No. 28 | Anh T\u00fa Ng\u00f4",
        "rank": "28",
        "score": "2,485",
        "username": "Anh T\u00fa Ng\u00f4"
    },
    "b8300a915ead93bf57a79adf0a58d9c6": {
        "label": "No. 29 | Yuzhou Chen",
        "rank": "29",
        "score": "2,410",
        "username": "Yuzhou Chen"
    },
    "cdc173e7949f13947fdd62fedc8207f9": {
        "label": "No. 30 | Mythri Shivakumar",
        "rank": "30",
        "score": "2,380",
        "username": "Mythri Shivakumar"
    },
    "b76158b7674a742649011d58d4fd189e": {
        "label": "No. 31 | Vick Mahase",
        "rank": "31",
        "score": "2,345",
        "username": "Vick Mahase"
    },
    "6ceba249f442dc176a256fd3eced86d3": {
        "label": "No. 32 | Shi-Wei Zhou",
        "rank": "32",
        "score": "2,325",
        "username": "Shi-Wei Zhou"
    },
    "365368dbe7415a8b973899c4e59b25c6": {
        "label": "No. 33 | PythonPPP",
        "rank": "33",
        "score": "2,325",
        "username": "PythonPPP"
    },
    "5a665e8671177d2f02c54f07e7671cf8": {
        "label": "No. 34 | Breeze Chen",
        "rank": "34",
        "score": "2,295",
        "username": "Breeze Chen"
    },
    "652e48bb4e88c276e46a24a41b51f6f5": {
        "label": "No. 35 | anian.ruoss",
        "rank": "35",
        "score": "2,281.5",
        "username": "anian.ruoss"
    },
    "ed8b3d0228f70273478f4c17d342157f": {
        "label": "No. 36 | atoms-iambics.4i",
        "rank": "36",
        "score": "2,265",
        "username": "atoms-iambics.4i"
    },
    "b0ffdfd546c2cfe5688ab1e44f9ead8c": {
        "label": "No. 37 | M\u00e1rcio Pereira",
        "rank": "37",
        "score": "2,265",
        "username": "M\u00e1rcio Pereira"
    },
    "341933d74043bbdfcf5b0f518d1e6923": {
        "label": "No. 38 | Tushar aggarwal",
        "rank": "38",
        "score": "2,240",
        "username": "Tushar aggarwal"
    },
    "00363e58d1a918f28b5ecb94451167ef": {
        "label": "No. 39 | Nabeel Raza",
        "rank": "39",
        "score": "2,220",
        "username": "Nabeel Raza"
    },
    "97588afccc06ab598cbf941967e9afec": {
        "label": "No. 40 | bebeshka",
        "rank": "40",
        "score": "2,190",
        "username": "bebeshka"
    },
    "80185f4087ba0ef6c4c4b6d59679792f": {
        "label": "No. 41 | soumit saha",
        "rank": "41",
        "score": "2,185",
        "username": "soumit saha"
    },
    "26251a8afdb1afb5dd441c9602882dd6": {
        "label": "No. 42 | Zeyuan Li",
        "rank": "42",
        "score": "2,150",
        "username": "Zeyuan Li"
    },
    "6081482d75dc29a31ff28ede48b83c24": {
        "label": "No. 43 | Youshaa Murhij",
        "rank": "43",
        "score": "2,135",
        "username": "Youshaa Murhij"
    },
    "8812c36aa5ae336c2a77bf63211d899a": {
        "label": "No. 44 | ps",
        "rank": "44",
        "score": "2,125",
        "username": "ps"
    },
    "7941424184cb93233f0fe1d7cbd2d623": {
        "label": "No. 45 | romil797",
        "rank": "45",
        "score": "2,120",
        "username": "romil797"
    },
    "5d168300eba3c7081ebeaefce162fd28": {
        "label": "No. 46 | callrmshetty",
        "rank": "46",
        "score": "2,102.5",
        "username": "callrmshetty"
    },
    "bcc06a67840b720cd9efbda275e40fba": {
        "label": "No. 47 | Kapish Luhariwala",
        "rank": "47",
        "score": "2,090",
        "username": "Kapish Luhariwala"
    },
    "5f7f7ef6f4bec0224a111e3b550a521b": {
        "label": "No. 48 | yang_mingxin",
        "rank": "48",
        "score": "2,020",
        "username": "yang_mingxin"
    },
    "5db484f28576abd42a6b47fb50ff9774": {
        "label": "No. 49 | s233036",
        "rank": "49",
        "score": "2,015",
        "username": "s233036"
    },
    "73f4d220e9f4f6940d1f8e052ee7148a": {
        "label": "No. 50 | vijaybharathi1998",
        "rank": "50",
        "score": "1,985",
        "username": "vijaybharathi1998"
    },
    "b5486fd563465d499ef650bd64ff4c54": {
        "label": "No. 51 | Aykut \u00c7ay\u0131r",
        "rank": "51",
        "score": "1,985",
        "username": "Aykut \u00c7ay\u0131r"
    },
    "849125c0ec10fed35d34a8cc9ec02883": {
        "label": "No. 52 | Mahesh Mantri",
        "rank": "52",
        "score": "1,980",
        "username": "Mahesh Mantri"
    },
    "fb49308c3cb0cb3e49b043dc720258ef": {
        "label": "No. 53 | Shooshi",
        "rank": "53",
        "score": "1,980",
        "username": "Shooshi"
    },
    "0c7bfef761389637a1171aa1faaa0a37": {
        "label": "No. 54 | Ivan Koptiev",
        "rank": "54",
        "score": "1,975.5",
        "username": "Ivan Koptiev"
    },
    "1a3ec3eb185ee8c66e9f6a63e6639422": {
        "label": "No. 55 | Kacper Urban",
        "rank": "55",
        "score": "1,925",
        "username": "Kacper Urban"
    },
    "3b3e17601b9c589917314161f80aa6ca": {
        "label": "No. 56 | NIESCHAL GHOSH",
        "rank": "56",
        "score": "1,910",
        "username": "NIESCHAL GHOSH"
    },
    "313977db97b224206981e0e203c45ad6": {
        "label": "No. 57 | Eric Xia",
        "rank": "57",
        "score": "1,895",
        "username": "Eric Xia"
    },
    "18d499d0bcf0683320169d138a879425": {
        "label": "No. 58 | 0x researcher",
        "rank": "58",
        "score": "1,890",
        "username": "0x researcher"
    },
    "f1f1dfb0392f0b8e26eac63f03a0ed13": {
        "label": "No. 59 | Ma Al",
        "rank": "59",
        "score": "1,865",
        "username": "Ma Al"
    },
    "52510a2a3e2f0948af617107295ba048": {
        "label": "No. 60 | Shubh Goyal",
        "rank": "60",
        "score": "1,860",
        "username": "Shubh Goyal"
    },
    "48a987c9855bc4607f979052e196666b": {
        "label": "No. 61 | Alper Karaca",
        "rank": "61",
        "score": "1,855",
        "username": "Alper Karaca"
    },
    "f80742b6f8c95cb6c93671ad71ad392f": {
        "label": "No. 62 | Alex Shcherbakov",
        "rank": "62",
        "score": "1,850",
        "username": "Alex Shcherbakov"
    },
    "f286651bcbd604ccf7a00f616ce41bd5": {
        "label": "No. 63 | Wenxuan Dai",
        "rank": "63",
        "score": "1,825",
        "username": "Wenxuan Dai"
    },
    "3d24fafd2137bffe278b5eb2cbc1aeac": {
        "label": "No. 64 | Max Ling",
        "rank": "64",
        "score": "1,815",
        "username": "Max Ling"
    },
    "0aae0d7cfa9f163e90039fb8460506dc": {
        "label": "No. 65 | automorphing",
        "rank": "65",
        "score": "1,815",
        "username": "automorphing"
    },
    "8a90e70f9a5ef59aa06b938be375bf32": {
        "label": "No. 66 | Qiujiang Jin",
        "rank": "66",
        "score": "1,810",
        "username": "Qiujiang Jin"
    },
    "cf59a2dd38afd207a0edfa957a14cb4e": {
        "label": "No. 67 | Kyle Zhou",
        "rank": "67",
        "score": "1,805",
        "username": "Kyle Zhou"
    },
    "d4248ae25224a9ad44dab3658985836e": {
        "label": "No. 68 | Aarohi Bhand",
        "rank": "68",
        "score": "1,785",
        "username": "Aarohi Bhand"
    },
    "208f9352c084733e429785cec277d70a": {
        "label": "No. 69 | Alex Mason",
        "rank": "69",
        "score": "1,775",
        "username": "Alex Mason"
    },
    "ab00124a778fa26a75c3b2a78189222d": {
        "label": "No. 70 | tanghaibao",
        "rank": "70",
        "score": "1,755",
        "username": "tanghaibao"
    },
    "a1ef8e1c2382ffb88d4f6968535d72dc": {
        "label": "No. 71 | firstuserhere",
        "rank": "71",
        "score": "1,750.5",
        "username": "firstuserhere"
    },
    "2e71056725ab50c8bedccfd26465a1c2": {
        "label": "No. 72 | Junang Li",
        "rank": "72",
        "score": "1,745",
        "username": "Junang Li"
    },
    "4d86c7e717cfe667cd976a81791b14c9": {
        "label": "No. 73 | 747893812",
        "rank": "73",
        "score": "1,725",
        "username": "747893812"
    },
    "10c35409e9bebe5d858862c5cf6bccee": {
        "label": "No. 74 | cynthiaxue2018",
        "rank": "74",
        "score": "1,715",
        "username": "cynthiaxue2018"
    },
    "6ec59fdd6df38e9452221a065dcd39ae": {
        "label": "No. 75 | Joe Chaoyue",
        "rank": "75",
        "score": "1,715",
        "username": "Joe Chaoyue"
    },
    "b174fe3078a811572fedaf2212ee79de": {
        "label": "No. 76 | Nikita Bekasov",
        "rank": "76",
        "score": "1,715",
        "username": "Nikita Bekasov"
    },
    "0932086ba146b101647939d26bede2f9": {
        "label": "No. 77 | monamie.b",
        "rank": "77",
        "score": "1,705",
        "username": "monamie.b"
    },
    "ea381d7a629173e7174d1189a8e64c4b": {
        "label": "No. 78 | Wu.E Jiang",
        "rank": "78",
        "score": "1,690",
        "username": "Wu.E Jiang"
    },
    "4a37c0235d1965519c1f5c9237cba7ba": {
        "label": "No. 79 | JiaYi Fu",
        "rank": "79",
        "score": "1,690",
        "username": "JiaYi Fu"
    },
    "4739829a5b9ab43a201ab0689883158c": {
        "label": "No. 80 | Xiao Lei Zhang",
        "rank": "80",
        "score": "1,685",
        "username": "Xiao Lei Zhang"
    },
    "cd2c0de42be598f11fb7959d271d261b": {
        "label": "No. 81 | Linxuan XIE",
        "rank": "81",
        "score": "1,675",
        "username": "Linxuan XIE"
    },
    "f3a79b16133427f54afec943fe8c0f72": {
        "label": "No. 82 | C\u00f4me Ox",
        "rank": "82",
        "score": "1,665",
        "username": "C\u00f4me Ox"
    },
    "4198a6558f3dbf8d8fa11fbf427bf9c4": {
        "label": "No. 83 | Samyak Jain",
        "rank": "83",
        "score": "1,645",
        "username": "Samyak Jain"
    },
    "d8f8f763037f2731664644d6e7d6e204": {
        "label": "No. 84 | Yi Zhang",
        "rank": "84",
        "score": "1,640",
        "username": "Yi Zhang"
    },
    "710ea5b4deca3447e2942aa4599d21ef": {
        "label": "No. 85 | Jason Fang",
        "rank": "85",
        "score": "1,633.795",
        "username": "Jason Fang"
    },
    "796090202769440b6085d42fecdbe8f8": {
        "label": "No. 86 | Ching Wei Tseng",
        "rank": "86",
        "score": "1,620",
        "username": "Ching Wei Tseng"
    },
    "584437150e11d60d113a58fd0da43845": {
        "label": "No. 87 | Peter Li",
        "rank": "87",
        "score": "1,620",
        "username": "Peter Li"
    },
    "511cd3f4651a2ee006a0362d783719a5": {
        "label": "No. 88 | Maksim Nikolin",
        "rank": "88",
        "score": "1,618",
        "username": "Maksim Nikolin"
    },
    "f0b5e65ef523bab984ed53ba4b728069": {
        "label": "No. 89 | yd.nan",
        "rank": "89",
        "score": "1,617.8",
        "username": "yd.nan"
    },
    "751081d58f2e19f4003aa64ca1515ba6": {
        "label": "No. 90 | zhiheng xu",
        "rank": "90",
        "score": "1,610",
        "username": "zhiheng xu"
    },
    "2574fc1950ead623e524e330ab9c6e1f": {
        "label": "No. 91 | Yin Xiaoln",
        "rank": "91",
        "score": "1,610",
        "username": "Yin Xiaoln"
    },
    "c320dcc7c47c7fa77178df8e1c41c671": {
        "label": "No. 92 | Aditya Lambat",
        "rank": "92",
        "score": "1,605",
        "username": "Aditya Lambat"
    },
    "ec57c08aec4b3c72a528e878f74685a7": {
        "label": "No. 93 | Sergey",
        "rank": "93",
        "score": "1,600",
        "username": "Sergey"
    },
    "3648418059096f6603a8bcfcb0610a1e": {
        "label": "No. 94 | Sirui Zheng",
        "rank": "94",
        "score": "1,590",
        "username": "Sirui Zheng"
    },
    "abbd62eadca021ffff1c6baab6204cbb": {
        "label": "No. 95 | x15144067268",
        "rank": "95",
        "score": "1,560",
        "username": "x15144067268"
    },
    "dc18d83abfd9f87d396e8fd6b6ac0fe1": {
        "label": "No. 96 | ZZ",
        "rank": "96",
        "score": "1,555",
        "username": "ZZ"
    },
    "5193e1e3407c3e144c5a93bba917664f": {
        "label": "No. 97 | Phu Pham Gia Tran",
        "rank": "97",
        "score": "1,550",
        "username": "Phu Pham Gia Tran"
    },
    "17cc7540cf08b5c2362d11998c17f728": {
        "label": "No. 98 | md faiyaz abdullah sayeedi",
        "rank": "98",
        "score": "1,545",
        "username": "md faiyaz abdullah sayeedi"
    },
    "2f741fa4c18e28cb6884290e09530897": {
        "label": "No. 99 | Chi Yang",
        "rank": "99",
        "score": "1,540.5",
        "username": "Chi Yang"
    },
    "a53573300f3804c9f13829bed755b85d": {
        "label": "No. 100 | Nicolas De Bie",
        "rank": "100",
        "score": "1,519.132",
        "username": "Nicolas De Bie"
    }
}